README.md
setup.cfg
setup.py
prisma_sdwan_get_all_interface_info/__init__.py
prisma_sdwan_get_all_interface_info.egg-info/PKG-INFO
prisma_sdwan_get_all_interface_info.egg-info/SOURCES.txt
prisma_sdwan_get_all_interface_info.egg-info/dependency_links.txt
prisma_sdwan_get_all_interface_info.egg-info/entry_points.txt
prisma_sdwan_get_all_interface_info.egg-info/requires.txt
prisma_sdwan_get_all_interface_info.egg-info/top_level.txt