Metadata-Version: 2.1
Name: prisma-sdwan-get-all-interface-info
Version: 2.0.1
Summary: Utility to dump all CloudGenix App Fabric Interface configurations to a CSV.
Home-page: https://github.com/ebob9/get-all-interface-info
Author: Aaron Edwards
Author-email: prisma_sdwan_get_all_interface_info@ebob9.com
License: MIT
Classifier: Development Status :: 5 - Production/Stable
Classifier: Intended Audience :: Developers
Classifier: License :: OSI Approved :: MIT License
Classifier: Programming Language :: Python :: 3
